[{"hero":"Randall","total":558},{"hero":"Animal","total":509},{"hero":"Timon.Pumbaa","total":429},{"hero":"Megara","total":346},{"hero":"Joy","total":333},{"hero":"Hook","total":321},{"hero":"Mulan","total":301},{"hero":"Hades","total":219},{"hero":"Jafar","total":217},{"hero":"Goofy","total":196},{"hero":"Kristoff.Sven","total":170},{"hero":"Donald","total":164},{"hero":"Peter.Pan","total":157},{"hero":"Beast","total":154},{"hero":"Miss.Piggy","total":149},{"hero":"Rapunzel","total":147},{"hero":"Maleficent","total":140},{"hero":"Magica","total":138},{"hero":"Stitch","total":135},{"hero":"Li.Shang","total":117},{"hero":"Maximus","total":110},{"hero":"Felix","total":101},{"hero":"Ducky.Bunny","total":94},{"hero":"Gaston","total":86},{"hero":"Tron","total":86},{"hero":"Gonzo","total":84},{"hero":"Rafiki","total":83},{"hero":"Bo.Peep","total":82},{"hero":"Baymax","total":81},{"hero":"Elsa","total":80},{"hero":"Anger","total":75},{"hero":"Launchpad","total":62},{"hero":"Pooh","total":58},{"hero":"Dash","total":53},{"hero":"Duke.Caboom","total":52},{"hero":"Jasmine","total":51},{"hero":"Olaf","total":47},{"hero":"Pleakley","total":47},{"hero":"Cheshire.Cat","total":47},{"hero":"Oogie","total":43},{"hero":"Powerline","total":41},{"hero":"King.Louie","total":41},{"hero":"Megavolt","total":40},{"hero":"Shan.Yu","total":39},{"hero":"Huey.D.L","total":35},{"hero":"Minnie","total":34},{"hero":"Moana","total":32},{"hero":"Linguini","total":32},{"hero":"Angel","total":32},{"hero":"Quorra","total":30},{"hero":"Ian.Lightfoot","total":29},{"hero":"Scar","total":28},{"hero":"Davy.Jones","total":27},{"hero":"Barbossa","total":26},{"hero":"Yzma","total":25},{"hero":"Merlin","total":24},{"hero":"Jumba","total":24},{"hero":"Scrooge","total":23},{"hero":"Colette","total":23},{"hero":"Goliath","total":23},{"hero":"Slinky","total":23},{"hero":"Kida","total":22},{"hero":"Mushu","total":21},{"hero":"Hank.Dory","total":20},{"hero":"Nick.Wilde","total":19},{"hero":"Merida","total":18},{"hero":"Mr.Incredible","total":16},{"hero":"Hiro","total":16},{"hero":"Sulley","total":15},{"hero":"Mickey","total":15},{"hero":"Gerald.M.N","total":15},{"hero":"Syndrome","total":15},{"hero":"Simba.Nala","total":13},{"hero":"Facilier","total":13},{"hero":"Yax","total":12},{"hero":"Hercules","total":12},{"hero":"Violet","total":11},{"hero":"Flynn.Rider","total":11},{"hero":"Evil.Queen","total":11},{"hero":"Madam.Mim","total":10},{"hero":"Flynn","total":10},{"hero":"Belle","total":10},{"hero":"Zurg","total":9},{"hero":"Mad.Hatter","total":9},{"hero":"Queen.of.Hearts","total":9},{"hero":"Eeyore","total":9},{"hero":"Finnick","total":8},{"hero":"Gizmo","total":8},{"hero":"Judy.Hopps","total":8},{"hero":"Rex","total":7},{"hero":"Woody","total":7},{"hero":"Jack.Jack","total":7},{"hero":"Basil","total":7},{"hero":"Mike","total":6},{"hero":"Ursula","total":6},{"hero":"Jack.Sparrow","total":6},{"hero":"Sally","total":6},{"hero":"Kim.Possible","total":6},{"hero":"Frozone","total":5},{"hero":"WallE","total":5},{"hero":"Calhoun","total":5},{"hero":"Tia.Dalma","total":5},{"hero":"Robin.Hood","total":5},{"hero":"Tigger","total":5},{"hero":"Baloo","total":5},{"hero":"Eve","total":4},{"hero":"Miguel","total":4},{"hero":"Elasticgirl","total":4},{"hero":"Jack.Skellington","total":4},{"hero":"Alice","total":3},{"hero":"Buzz","total":3},{"hero":"Dark.Wing","total":3},{"hero":"Maui","total":3},{"hero":"Amelia","total":3},{"hero":"Genie","total":2},{"hero":"Aladdin","total":2},{"hero":"Bogo","total":2},{"hero":"Shank","total":1},{"hero":"Jessie","total":1}]